{
  "type": "FeatureCollection",
  "features": [
    {
      "type": "Feature",
      "geometry": {
        "type": "Point",
        "coordinates": [
          14.37761,
          50.0831468
        ]
      },
      "properties": {
        "@type": "node",
        "@id": 3304591377,
        "@url": "https://www.openstreetmap.org/node/3304591377",
        "addr:city": "Praha 6",
        "addr:housenumber": "8",
        "addr:postcode": "16900",
        "addr:street": "Závěrka",
        "email": "helpdesk@spoje.net",
        "internet_access": "service",
        "name": "SPOJE.NET s.r.o.",
        "note": "Internet Service Provider, Server housing, Virtual servers, Webhosting, Mailhosting, Fiber optics, Wi-Fi, Security systems, CCTV, General help with computers. Possible to individually negotiate payment in cryptocurrencies using mail, phone or in person.",
        "office": "it",
        "opening_hours": "Mo-Fr 9:00-19:00",
        "payment:bitcoin": "yes",
        "payment:cash": "yes",
        "payment:paypal": "yes",
        "payment:wire_transfer": "yes",
        "phone": "+420 608 233 232",
        "recycling:low_energy_bulbs": "yes",
        "recycling:printer_cartridges": "yes",
        "recycling:small_appliances": "yes",
        "shop": "computer",
        "website": "http://www.spoje.net/"
      }
    },
    {
      "type": "Feature",
      "geometry": {
        "type": "Point",
        "coordinates": [
          16.7625302,
          50.0835571
        ]
      },
      "properties": {
        "@type": "node",
        "@id": 4309170164,
        "@url": "https://www.openstreetmap.org/node/4309170164",
        "name": "Elektro",
        "opening_hours": "Mo-Fr 08:00-12:00,13:00-17:00; Sa 08:00-11:30; Su,PH off",
        "operator": "Proton",
        "recycling:electrical_appliances": "yes",
        "shop": "electronics"
      }
    },
    {
      "type": "Feature",
      "geometry": {
        "type": "Point",
        "coordinates": [
          14.3639868,
          50.199886
        ]
      },
      "properties": {
        "@type": "node",
        "@id": 10183461017,
        "@url": "https://www.openstreetmap.org/node/10183461017",
        "amenity": "waste_basket",
        "level": "0",
        "recycling:cans": "yes",
        "recycling:paper": "yes",
        "recycling:plastic": "yes",
        "recycling:waste": "yes"
      }
    }
  ]
}
