{
  "type": "FeatureCollection",
  "features": [
    {
      "type": "Feature",
      "geometry": {
        "type": "Point",
        "coordinates": [
          14.37761,
          50.0831468
        ]
      },
      "properties": {
        "@type": "node",
        "@id": 3304591377,
        "@url": "https://www.openstreetmap.org/node/3304591377",
        "addr:city": "Praha 6",
        "addr:housenumber": "8",
        "addr:postcode": "16900",
        "addr:street": "Závěrka",
        "email": "helpdesk@spoje.net",
        "internet_access": "service",
        "name": "SPOJE.NET s.r.o.",
        "note": "Internet Service Provider, Server housing, Virtual servers, Webhosting, Mailhosting, Fiber optics, Wi-Fi, Security systems, CCTV, General help with computers. Possible to individually negotiate payment in cryptocurrencies using mail, phone or in person.",
        "office": "it",
        "opening_hours": "Mo-Fr 9:00-19:00",
        "payment:cash": "yes",
        "payment:paypal": "yes",
        "payment:wire_transfer": "yes",
        "phone": "+420 608 233 232",
        "recycling:low_energy_bulbs": "yes",
        "recycling:printer_cartridges": "yes",
        "recycling:small_appliances": "yes",
        "shop": "computer",
        "website": "http://www.spoje.net/"
      }
    },
    {
      "type": "Feature",
      "geometry": {
        "type": "Point",
        "coordinates": [
          16.646353,
          49.6021901
        ]
      },
      "properties": {
        "@type": "node",
        "@id": 10815335002,
        "@url": "https://www.openstreetmap.org/node/10815335002",
        "recycling:batteries": "no",
        "recycling:cooking_oil": "yes",
        "recycling:electrical_appliances": "no",
        "recycling:electrical_items": "no",
        "recycling:fluorescent_tubes": "no",
        "recycling:hazardous_waste": "no",
        "recycling:low_energy_bulbs": "no",
        "recycling:rubble": "no",
        "recycling:tyres": "no",
        "recycling:wood": "no"
      }
    }
  ]
}
