{
  "type": "FeatureCollection",
  "features": [
    {
      "type": "Feature",
      "geometry": {
        "type": "Point",
        "coordinates": [
          15.0304658,
          50.0921037
        ]
      },
      "properties": {
        "@type": "node",
        "@id": 12723845771,
        "@url": "https://www.openstreetmap.org/node/12723845771",
        "amenity": "public_bookcase",
        "name": "Daruj knihy",
        "recycling:clothes": "yes"
      }
    }
  ]
}
